{
    "sheet_url": "https://script.google.com/macros/s/AKfycbx3Fkssdo4QIO2YBPPOEEzuEdedoiYqyRxC8Cuna5OacrO4Bump/exec",
    "products_hash": "showroom_products",
    "looks_ref": "/looks/looks-NOCACHE.json",
    "showrooms": [
        {
            "title": "Delta",
            "image": "https://viewer.byondxr.com/content/1198/1669e76f_19ca_4ef1_b434_6c6de9e5ced6.png",
            "id": "/showroooms/showroom-delta-NOCACHE.json",
            "description": "Delta demo Showroom",
            "created_date": "",
            "updated_date": "",
            "owner": ""
        }
    ]
}